doculyzer/__init__.py
doculyzer/config.py
doculyzer/configure_logging.py
doculyzer/crawler.py
doculyzer/main.py
doculyzer/search.py
doculyzer/server.py
doculyzer/vendor.py
doculyzer/adapter/__init__.py
doculyzer/adapter/base.py
doculyzer/adapter/confluence.py
doculyzer/adapter/database.py
doculyzer/adapter/enhanced_content.py
doculyzer/adapter/factory.py
doculyzer/adapter/file.py
doculyzer/adapter/jira.py
doculyzer/adapter/mongodb.py
doculyzer/adapter/s3.py
doculyzer/adapter/servicenow.py
doculyzer/adapter/web.py
doculyzer/content_source/__init__.py
doculyzer/content_source/base.py
doculyzer/content_source/confluence.py
doculyzer/content_source/database.py
doculyzer/content_source/factory.py
doculyzer/content_source/file.py
doculyzer/content_source/google_drive.py
doculyzer/content_source/jira.py
doculyzer/content_source/mongodb.py
doculyzer/content_source/s3.py
doculyzer/content_source/servicenow.py
doculyzer/content_source/sharepoint.py
doculyzer/content_source/utils.py
doculyzer/content_source/web.py
doculyzer/document_parser/__init__.py
doculyzer/document_parser/base.py
doculyzer/document_parser/csv.py
doculyzer/document_parser/document_type_detector.py
doculyzer/document_parser/docx.py
doculyzer/document_parser/extract_dates.py
doculyzer/document_parser/factory.py
doculyzer/document_parser/html.py
doculyzer/document_parser/json.py
doculyzer/document_parser/lru_cache.py
doculyzer/document_parser/markdown.py
doculyzer/document_parser/pdf.py
doculyzer/document_parser/pptx.py
doculyzer/document_parser/temporal_semantics.py
doculyzer/document_parser/text.py
doculyzer/document_parser/xlsx.py
doculyzer/document_parser/xml.py
doculyzer/embeddings/__init__.py
doculyzer/embeddings/base.py
doculyzer/embeddings/contextual_embedding.py
doculyzer/embeddings/factory.py
doculyzer/embeddings/fastembed.py
doculyzer/embeddings/hugging_face.py
doculyzer/embeddings/openai.py
doculyzer/relationships/__init__.py
doculyzer/relationships/base.py
doculyzer/relationships/composite.py
doculyzer-0.41.0.dist-info/licenses/LICENSE
doculyzer-0.41.0.dist-info/METADATA
doculyzer-0.41.0.dist-info/WHEEL
doculyzer-0.41.0.dist-info/top_level.txt
doculyzer-0.41.0.dist-info/RECORD
