Metadata-Version: 2.4
Name: doculyzer
Version: 0.41.0
Summary: Universal, Searchable, Structured Document Manager
Author-email: Kenneth Stott <ken@hasura.io>
License: MIT
Project-URL: homepage, https://github.com/hasura/doculyzer
Project-URL: repository, https://github.com/hasura/doculyzer
Project-URL: documentation, https://github.com/hasura/doculyzer/wiki
Project-URL: issues, https://github.com/hasura/doculyzer/issues
Keywords: document-management,semantic-search,embedding,document-parsing
Classifier: Development Status :: 3 - Alpha
Classifier: Intended Audience :: Developers
Classifier: License :: OSI Approved :: MIT License
Classifier: Programming Language :: Python :: 3
Classifier: Programming Language :: Python :: 3.9
Classifier: Programming Language :: Python :: 3.10
Classifier: Programming Language :: Python :: 3.11
Classifier: Topic :: Text Processing
Classifier: Topic :: Database
Classifier: Natural Language :: English
License-File: LICENSE
Requires-Dist: lxml~=5.4.0
Requires-Dist: PyYAML~=6.0.2
Requires-Dist: beautifulsoup4~=4.13.4
Requires-Dist: Markdown~=3.8
Requires-Dist: requests~=2.32.3
Requires-Dist: pydantic~=2.11.4
Requires-Dist: python-docx~=1.1.2
Requires-Dist: openpyxl~=3.1.5
Requires-Dist: pymupdf~=1.25.5
Requires-Dist: python-pptx~=1.0.2
Requires-Dist: datefinder~=0.7.3
Requires-Dist: python-dateutil~=2.9.0
Requires-Dist: jsonpath-ng~=1.7.0
Requires-Dist: python-dotenv~=1.1.0
Requires-Dist: wcmatch~=10.0
Provides-Extra: development
Requires-Dist: pytest~=8.3.5; extra == "development"
Requires-Dist: build~=1.2.2; extra == "development"
Provides-Extra: db-core
Requires-Dist: sqlean.py~=3.47.0; platform_system == "Darwin" and extra == "db-core"
Requires-Dist: sqlean.py~=3.47.0; (platform_system == "Linux" and platform_machine == "x86_64") and extra == "db-core"
Requires-Dist: SQLAlchemy~=2.0.40; extra == "db-core"
Provides-Extra: scientific
Requires-Dist: numpy~=2.0.2; extra == "scientific"
Provides-Extra: huggingface
Requires-Dist: torch==2.7.0; extra == "huggingface"
Requires-Dist: sentence-transformers~=4.1.0; extra == "huggingface"
Provides-Extra: openai
Requires-Dist: openai~=1.76.0; extra == "openai"
Provides-Extra: fastembed
Requires-Dist: fastembed>=0.1.0; extra == "fastembed"
Provides-Extra: embedding-all
Requires-Dist: torch==2.7.0; extra == "embedding-all"
Requires-Dist: sentence-transformers~=4.1.0; extra == "embedding-all"
Requires-Dist: openai~=1.76.0; extra == "embedding-all"
Requires-Dist: fastembed>=0.1.0; extra == "embedding-all"
Provides-Extra: default
Requires-Dist: torch==2.7.0; extra == "default"
Requires-Dist: sentence-transformers~=4.1.0; extra == "default"
Provides-Extra: document-parsing
Requires-Dist: python-magic~=0.4.27; extra == "document-parsing"
Provides-Extra: db-mongodb
Requires-Dist: pymongo~=4.12.0; extra == "db-mongodb"
Provides-Extra: db-elasticsearch
Requires-Dist: elasticsearch~=9.0.1; extra == "db-elasticsearch"
Provides-Extra: db-postgresql
Requires-Dist: psycopg2-binary~=2.9.10; extra == "db-postgresql"
Provides-Extra: db-mysql
Requires-Dist: mysql-connector-python~=9.3.0; extra == "db-mysql"
Provides-Extra: db-neo4j
Requires-Dist: neo4j~=5.28.1; extra == "db-neo4j"
Provides-Extra: db-libsql
Requires-Dist: libsql-client~=0.3.1; extra == "db-libsql"
Provides-Extra: db-solr
Requires-Dist: pysolr~=3.10.0; extra == "db-solr"
Provides-Extra: db-vector
Requires-Dist: pgvector>=0.2.0; extra == "db-vector"
Requires-Dist: sqlite-vec>=0.1.0; extra == "db-vector"
Requires-Dist: sqlite-vss>=0.1.0; extra == "db-vector"
Provides-Extra: cloud-aws
Requires-Dist: boto3~=1.38.3; extra == "cloud-aws"
Requires-Dist: botocore~=1.38.4; extra == "cloud-aws"
Provides-Extra: source-database
Requires-Dist: SQLAlchemy~=2.0.40; extra == "source-database"
Provides-Extra: source-confluence
Requires-Dist: atlassian-python-api~=3.41.9; extra == "source-confluence"
Provides-Extra: source-jira
Requires-Dist: atlassian-python-api~=3.41.9; extra == "source-jira"
Provides-Extra: source-servicenow
Requires-Dist: pysnow~=0.7.17; extra == "source-servicenow"
Provides-Extra: source-mongodb
Requires-Dist: pymongo~=4.12.0; extra == "source-mongodb"
Provides-Extra: source-sharepoint
Requires-Dist: Office365-REST-Python-Client~=2.5.0; extra == "source-sharepoint"
Provides-Extra: source-gdrive
Requires-Dist: google-api-python-client~=2.36.0; extra == "source-gdrive"
Requires-Dist: google-auth-oauthlib~=1.0.0; extra == "source-gdrive"
Provides-Extra: source-all
Requires-Dist: SQLAlchemy~=2.0.40; extra == "source-all"
Requires-Dist: atlassian-python-api~=3.41.9; extra == "source-all"
Requires-Dist: pysnow~=0.7.17; extra == "source-all"
Requires-Dist: pymongo~=4.12.0; extra == "source-all"
Requires-Dist: Office365-REST-Python-Client~=2.5.0; extra == "source-all"
Requires-Dist: google-api-python-client~=2.36.0; extra == "source-all"
Requires-Dist: google-auth-oauthlib~=1.0.0; extra == "source-all"
Provides-Extra: db-all
Requires-Dist: sqlean.py~=3.47.0; platform_system == "Darwin" and extra == "db-all"
Requires-Dist: sqlean.py~=3.47.0; (platform_system == "Linux" and platform_machine == "x86_64") and extra == "db-all"
Requires-Dist: SQLAlchemy~=2.0.40; extra == "db-all"
Requires-Dist: pymongo~=4.12.0; extra == "db-all"
Requires-Dist: psycopg2-binary~=2.9.10; extra == "db-all"
Requires-Dist: mysql-connector-python~=9.3.0; extra == "db-all"
Requires-Dist: neo4j~=5.28.1; extra == "db-all"
Requires-Dist: libsql-client~=0.3.1; extra == "db-all"
Requires-Dist: pgvector>=0.2.0; extra == "db-all"
Requires-Dist: sqlite-vec>=0.1.0; extra == "db-all"
Requires-Dist: sqlite-vss>=0.1.0; extra == "db-all"
Provides-Extra: all
Requires-Dist: sqlean.py~=3.47.0; platform_system == "Darwin" and extra == "all"
Requires-Dist: sqlean.py~=3.47.0; (platform_system == "Linux" and platform_machine == "x86_64") and extra == "all"
Requires-Dist: SQLAlchemy~=2.0.40; extra == "all"
Requires-Dist: numpy~=2.0.2; extra == "all"
Requires-Dist: torch==2.7.0; extra == "all"
Requires-Dist: sentence-transformers~=4.1.0; extra == "all"
Requires-Dist: openai~=1.76.0; extra == "all"
Requires-Dist: fastembed>=0.1.0; extra == "all"
Requires-Dist: pymongo~=4.12.0; extra == "all"
Requires-Dist: psycopg2-binary~=2.9.10; extra == "all"
Requires-Dist: mysql-connector-python~=9.3.0; extra == "all"
Requires-Dist: neo4j~=5.28.1; extra == "all"
Requires-Dist: libsql-client~=0.3.1; extra == "all"
Requires-Dist: pgvector>=0.2.0; extra == "all"
Requires-Dist: sqlite-vec>=0.1.0; extra == "all"
Requires-Dist: sqlite-vss>=0.1.0; extra == "all"
Requires-Dist: pysolr>=3.10.0; extra == "all"
Requires-Dist: atlassian-python-api~=3.41.9; extra == "all"
Requires-Dist: pysnow~=0.7.17; extra == "all"
Requires-Dist: Office365-REST-Python-Client~=2.5.0; extra == "all"
Requires-Dist: google-api-python-client~=2.36.0; extra == "all"
Requires-Dist: google-auth-oauthlib~=1.0.0; extra == "all"
Requires-Dist: boto3~=1.38.3; extra == "all"
Requires-Dist: botocore~=1.38.4; extra == "all"
Requires-Dist: python-magic~=0.4.27; extra == "all"
Requires-Dist: pytest~=8.3.5; extra == "all"
Requires-Dist: build~=1.2.2; extra == "all"
Provides-Extra: minimal
Dynamic: license-file
